{
"autoplayBgm":false,"autoplayBgs":false,"battleback1Name":"","battleback2Name":"","bgm":{"name":"","pan":0,"pitch":100,"volume":90},"bgs":{"name":"","pan":0,"pitch":100,"volume":90},"disableDashing":false,"displayName":"","encounterList":[],"encounterStep":30,"height":12,"note":"","parallaxLoopX":false,"parallaxLoopY":false,"parallaxName":"","parallaxShow":true,"parallaxSx":0,"parallaxSy":0,"scrollType":0,"specifyBattleback":false,"tilesetId":7,"width":12,
"data":[6012,6012,6012,6012,6012,6012,6012,6012,6012,6012,6012,6012,6379,6378,6378,6378,6378,6378,6378,6378,6378,6378,6378,6382,3604,3604,3604,3604,3604,3604,3604,3604,3604,3604,3604,3604,3584,3584,3584,3584,3584,3584,3584,3584,3584,3584,3584,3584,3584,3584,3584,3584,3584,3584,3584,3584,3584,3584,3584,3584,3584,3584,3584,3584,3584,3584,3584,3584,3584,3584,3584,3584,3584,3584,3584,3584,3584,3584,3584,3584,3584,3584,3584,3584,3584,3584,3584,3584,3584,3584,3584,3584,3584,3584,3584,3584,3584,3584,3584,3584,3584,3584,3584,3584,3584,3584,3584,3584,3584,3584,3584,3584,3584,3584,3584,3584,3584,3584,3584,3584,3612,3612,3612,3612,3612,3612,3612,3612,3612,3612,3612,3612,6004,6004,6004,6004,6004,6004,6004,6004,6004,6004,6004,6004,0,0,0,0,0,0,0,0,0,0,0,0,0,0,0,0,0,0,0,0,0,0,0,0,0,3054,0,0,0,0,0,0,0,0,3054,0,3053,0,0,0,0,0,0,0,0,0,0,3051,0,0,0,0,0,0,0,0,0,0,0,0,0,0,0,0,0,0,0,0,0,0,0,0,0,0,0,0,0,0,0,0,0,0,0,0,0,0,0,0,0,0,0,0,0,0,0,0,0,0,0,0,0,0,0,0,0,0,0,0,0,0,0,0,0,0,0,0,0,0,0,0,0,0,0,0,0,0,0,0,0,0,0,0,0,0,0,0,0,0,0,0,0,0,0,0,0,0,0,0,0,0,0,0,0,0,0,0,0,0,0,0,0,0,0,0,0,0,0,0,0,0,0,0,0,0,0,0,0,0,0,0,0,0,0,0,0,0,0,0,0,0,0,0,0,0,0,0,0,0,0,0,0,0,0,0,0,0,0,0,0,0,0,0,0,0,0,0,0,0,0,0,0,0,0,0,0,0,0,0,0,0,0,0,0,0,0,0,0,0,0,0,0,0,0,0,0,0,0,0,0,0,0,0,0,0,0,0,0,0,0,0,0,0,0,0,0,0,0,0,0,0,0,0,0,0,0,0,0,0,0,0,0,0,0,0,0,0,0,0,0,0,0,0,0,0,0,0,0,0,0,0,0,0,0,0,0,2,0,0,0,0,0,0,0,0,0,0,0,0,0,0,0,0,0,0,0,0,0,0,0,0,0,0,0,0,0,0,0,0,0,0,0,0,0,0,0,0,0,0,0,0,0,0,0,0,0,0,0,0,0,0,0,0,0,0,0,0,0,0,0,0,0,0,0,0,0,0,0,0,0,0,0,0,0,0,0,0,0,0,0,0,0,0,0,0,0,0,0,0,0,0,0,0,0,0,0,0,0,0,0,0,0,0,0,0,0,0,0,0,0,0,0,0,0,0,0,0,0,0,0,0,0,0,0,0,0,0,0,0,0,0,0,0,0,0,0,0,0,0,0,0,0,0,0,0,0,0,0,0,0,0,0,0,0,0,0,0,0,0,0,0,0,0,0,0,0,0,0,0,0,0,0,0,0,0,0,0,0,0,0,0,0,0,0,0,0,0,0,0,0,0,0,0,0,0,0,0,0,0,0,0,0,0,0,0,0,0,0,0,0,0,0,0,0,0,0,0,0,0,0,0,0,0,0,0,0,0,0,0,0,0,0,0,0,0,0,0,0,0,0,0,0,0,0,0,0,0,0,0,0,0,0,0,0,0,0,0,0,0,0,0,0,0,0,0,0,0,1,1,1,1,1,1,1,1,1,1,1,1,1,1,1,1,1,1,1,1,1,1,1,1,0,2,0,0,0,0,0,0,0,0,2,0,2,0,0,0,0,0,0,0,0,0,0,2,0,0,0,0,0,0,0,0,0,0,0,0,0,0,0,0,0,0,0,0,0,0,0,0,0,0,0,0,0,0,0,0,0,0,0,0,0,0,0,0,0,0,0,0,0,0,0,0,0,0,0,0,0,0,0,0,0,0,0,0,0,0,0,0,0,0,0,0,0,0,0,0,0,0,0,0,0,0,0,0,0,0,0,0,1,1,1,1,1,1,1,1,1,1,1,1],
"events":[
null,
null,
{"id":2,"name":"GoblinMan","note":"{\"type\":\"enemy\", \"class\":\"melee\", \"basehp\":1, \"attack\":1}","pages":[{"conditions":{"actorId":1,"actorValid":false,"itemId":1,"itemValid":false,"selfSwitchCh":"A","selfSwitchValid":false,"switch1Id":1,"switch1Valid":false,"switch2Id":1,"switch2Valid":false,"variableId":1,"variableValid":false,"variableValue":0},"directionFix":false,"image":{"tileId":0,"characterName":"Monster","direction":2,"pattern":1,"characterIndex":2},"list":[{"code":0,"indent":0,"parameters":[]}],"moveFrequency":3,"moveRoute":{"list":[{"code":0,"parameters":[]}],"repeat":true,"skippable":false,"wait":false},"moveSpeed":2,"moveType":0,"priorityType":1,"stepAnime":false,"through":false,"trigger":0,"walkAnime":true}],"x":0,"y":2},
{"id":3,"name":"GoblinMan","note":"{\"type\":\"enemy\", \"class\":\"melee\", \"basehp\":1, \"attack\":1}","pages":[{"conditions":{"actorId":1,"actorValid":false,"itemId":1,"itemValid":false,"selfSwitchCh":"A","selfSwitchValid":false,"switch1Id":1,"switch1Valid":false,"switch2Id":1,"switch2Valid":false,"variableId":1,"variableValid":false,"variableValue":0},"directionFix":false,"image":{"tileId":0,"characterName":"Monster","direction":2,"pattern":1,"characterIndex":2},"list":[{"code":0,"indent":0,"parameters":[]}],"moveFrequency":3,"moveRoute":{"list":[{"code":0,"parameters":[]}],"repeat":true,"skippable":false,"wait":false},"moveSpeed":2,"moveType":0,"priorityType":1,"stepAnime":false,"through":false,"trigger":0,"walkAnime":true}],"x":11,"y":2},
{"id":4,"name":"EV004","note":"","pages":[{"conditions":{"actorId":1,"actorValid":false,"itemId":1,"itemValid":false,"selfSwitchCh":"A","selfSwitchValid":false,"switch1Id":1,"switch1Valid":false,"switch2Id":1,"switch2Valid":false,"variableId":1,"variableValid":false,"variableValue":0},"directionFix":false,"image":{"tileId":2,"characterName":"","characterIndex":0,"direction":2,"pattern":0},"list":[{"code":111,"indent":0,"parameters":[1,2,0,0,2]},{"code":250,"indent":1,"parameters":[{"name":"Move1","volume":90,"pitch":100,"pan":0}]},{"code":355,"indent":1,"parameters":["BMM.HYB.mapCleanup();"]},{"code":201,"indent":1,"parameters":[0,20,5,13,0,0]},{"code":0,"indent":1,"parameters":[]},{"code":411,"indent":0,"parameters":[]},{"code":250,"indent":1,"parameters":[{"name":"Cancel1","volume":90,"pitch":100,"pan":0}]},{"code":101,"indent":1,"parameters":["",0,1,1]},{"code":401,"indent":1,"parameters":["KILL ALL ENEMIES TO PROCEED"]},{"code":0,"indent":1,"parameters":[]},{"code":412,"indent":0,"parameters":[]},{"code":0,"indent":0,"parameters":[]}],"moveFrequency":3,"moveRoute":{"list":[{"code":0,"parameters":[]}],"repeat":true,"skippable":false,"wait":false},"moveSpeed":3,"moveType":0,"priorityType":1,"stepAnime":false,"through":false,"trigger":0,"walkAnime":true}],"x":5,"y":1},
{"id":5,"name":"EV005","note":"","pages":[{"conditions":{"actorId":1,"actorValid":false,"itemId":1,"itemValid":false,"selfSwitchCh":"A","selfSwitchValid":false,"switch1Id":1,"switch1Valid":false,"switch2Id":1,"switch2Valid":false,"variableId":1,"variableValid":false,"variableValue":0},"directionFix":false,"image":{"tileId":0,"characterName":"fisherman","direction":2,"pattern":1,"characterIndex":4},"list":[{"code":123,"indent":0,"parameters":["A",0]},{"code":101,"indent":0,"parameters":["Actor2",0,0,2]},{"code":401,"indent":0,"parameters":["You can also damage enemies by using this "]},{"code":401,"indent":0,"parameters":["\\C[2]BOMB\\C."]},{"code":101,"indent":0,"parameters":["Actor2",0,0,2]},{"code":401,"indent":0,"parameters":["Drop the \\C[2]BOMB\\C by pressing \\C[1][1] and moving\\C "]},{"code":401,"indent":0,"parameters":["in any direction."]},{"code":101,"indent":0,"parameters":["Actor2",0,0,2]},{"code":401,"indent":0,"parameters":["The bomb will explode after time moves "]},{"code":401,"indent":0,"parameters":["forward 3 steps, damaging a 3x3 square."]},{"code":101,"indent":0,"parameters":["Actor2",0,0,2]},{"code":401,"indent":0,"parameters":["It will take eight steps for the bomb to "]},{"code":401,"indent":0,"parameters":["recharge."]},{"code":101,"indent":0,"parameters":["Actor2",0,0,2]},{"code":401,"indent":0,"parameters":["Use the bomb to hit those enemies in the "]},{"code":401,"indent":0,"parameters":["corner of the room."]},{"code":123,"indent":0,"parameters":["A",1]},{"code":123,"indent":0,"parameters":["B",0]},{"code":0,"indent":0,"parameters":[]}],"moveFrequency":3,"moveRoute":{"list":[{"code":0,"parameters":[]}],"repeat":true,"skippable":false,"wait":false},"moveSpeed":3,"moveType":0,"priorityType":1,"stepAnime":false,"through":false,"trigger":3,"walkAnime":true},{"conditions":{"actorId":1,"actorValid":false,"itemId":1,"itemValid":false,"selfSwitchCh":"A","selfSwitchValid":true,"switch1Id":1,"switch1Valid":false,"switch2Id":1,"switch2Valid":false,"variableId":1,"variableValid":false,"variableValue":0},"directionFix":false,"image":{"tileId":0,"characterName":"fisherman","direction":2,"pattern":1,"characterIndex":4},"list":[{"code":123,"indent":0,"parameters":["A",0]},{"code":0,"indent":0,"parameters":[]}],"moveFrequency":3,"moveRoute":{"list":[{"code":0,"parameters":[]}],"repeat":true,"skippable":false,"wait":false},"moveSpeed":3,"moveType":0,"priorityType":1,"stepAnime":false,"through":false,"trigger":3,"walkAnime":true},{"conditions":{"actorId":1,"actorValid":false,"itemId":1,"itemValid":false,"selfSwitchCh":"B","selfSwitchValid":true,"switch1Id":1,"switch1Valid":false,"switch2Id":1,"switch2Valid":false,"variableId":1,"variableValid":false,"variableValue":0},"directionFix":false,"image":{"characterIndex":0,"characterName":"","direction":2,"pattern":0,"tileId":0},"list":[{"code":123,"indent":0,"parameters":["B",0]},{"code":101,"indent":0,"parameters":["Actor2",0,0,2]},{"code":401,"indent":0,"parameters":["Drop a \\C[2]BOMB\\C by pressing \\C[1][1] and moving\\C."]},{"code":0,"indent":0,"parameters":[]}],"moveFrequency":3,"moveRoute":{"list":[{"code":0,"parameters":[]}],"repeat":true,"skippable":false,"wait":false},"moveSpeed":3,"moveType":0,"priorityType":0,"stepAnime":false,"through":false,"trigger":0,"walkAnime":true}],"x":8,"y":9}
]
}